ashcount/__init__.py
ashcount/ashcount.py
ashcount-1.0.1.dist-info/LICENSE
ashcount-1.0.1.dist-info/METADATA
ashcount-1.0.1.dist-info/WHEEL
ashcount-1.0.1.dist-info/top_level.txt
ashcount-1.0.1.dist-info/RECORD
